onboardbase/__init__.py
onboardbase/config.py
onboardbase/secrets.py
onboardbase/utils/__init__.py
onboardbase/utils/crypto.py
onboardbase/utils/server.py
onboardbase/utils/system.py
onboardbase/utils/url.py
onboardbase-0.0.3.dist-info/LICENSE.txt
onboardbase-0.0.3.dist-info/METADATA
onboardbase-0.0.3.dist-info/WHEEL
onboardbase-0.0.3.dist-info/top_level.txt
onboardbase-0.0.3.dist-info/RECORD
