Metadata-Version: 2.1
Name: onboardbase
Version: 0.0.3
Summary: Onboardbase python sdk
Home-page: http://pypi.python.org/pypi/onboardbase_v001.dev7/
Author: Ernest Offiong
Author-email: ernest.offiong@gmail.com
License: MIT
Classifier: Intended Audience :: Developers
Classifier: Topic :: Software Development :: Build Tools
Classifier: License :: OSI Approved :: MIT License
Classifier: Programming Language :: Python :: 3
Classifier: Programming Language :: Python :: 3.4
Classifier: Programming Language :: Python :: 3.5
Classifier: Programming Language :: Python :: 3.6
Requires-Python: >=3
License-File: LICENSE.txt
Requires-Dist: requests
Requires-Dist: pycryptodome
Requires-Dist: pythonmachineid
Requires-Dist: PyYAML
